aveas_openlabel/__init__.py
aveas_openlabel/attribute_enforcer.py
aveas_openlabel/attributes/__init__.py
aveas_openlabel/attributes/dimension.py
aveas_openlabel/attributes/general.py
aveas_openlabel/attributes/hmi_feedback.py
aveas_openlabel/attributes/impact.py
aveas_openlabel/attributes/interior.py
aveas_openlabel/attributes/lights.py
aveas_openlabel/attributes/open_drive.py
aveas_openlabel/attributes/operator.py
aveas_openlabel/attributes/road.py
aveas_openlabel/attributes/summary.py
aveas_openlabel/attributes/traffic.py
aveas_openlabel/aveas_openlabel.py
aveas_openlabel/classifications/__init__.py
aveas_openlabel/classifications/animal.py
aveas_openlabel/classifications/bicycle.py
aveas_openlabel/classifications/bus.py
aveas_openlabel/classifications/car.py
aveas_openlabel/classifications/human_pedestrian.py
aveas_openlabel/classifications/mobility_device.py
aveas_openlabel/classifications/motorcycle.py
aveas_openlabel/classifications/other_classification.py
aveas_openlabel/classifications/pushable_pullable.py
aveas_openlabel/classifications/railvehicle.py
aveas_openlabel/classifications/trailer.py
aveas_openlabel/classifications/truck.py
aveas_openlabel/classifications/van.py
aveas_openlabel/contexts/__init__.py
aveas_openlabel/contexts/environment_context.py
aveas_openlabel/contexts/environment_context_data.py
aveas_openlabel/contexts/scenario_context.py
aveas_openlabel/contexts/scenario_context_data.py
aveas_openlabel/event.py
aveas_openlabel/frame.py
aveas_openlabel/metadata.py
aveas_openlabel/object_data/__init__.py
aveas_openlabel/object_data/all.py
aveas_openlabel/object_data/unattached.py
aveas_openlabel/object_data/unsteerable.py
aveas_openlabel/object_data/unsteerable_non_operator.py
aveas_openlabel/object_data/unsteerable_unattached.py
aveas_openlabel/object_data/unsteerable_unattached_non_operator.py
aveas_openlabel/object_in_frame_data/__init__.py
aveas_openlabel/object_in_frame_data/all.py
aveas_openlabel/object_in_frame_data/no_rider.py
aveas_openlabel-0.4.17.dist-info/LICENSE
aveas_openlabel-0.4.17.dist-info/METADATA
aveas_openlabel-0.4.17.dist-info/WHEEL
aveas_openlabel-0.4.17.dist-info/RECORD
