Metadata-Version: 2.1
Name: aveas_openlabel
Version: 0.4.17
Summary: The AVEAS OpenLABEL specification
Home-page: https://github.com/understand-ai/aveas_openlabel
License: MIT
Keywords: ASAM OpenLABEL,AVEAS
Author: understand.ai
Author-email: postmaster@understand.ai
Requires-Python: >=3.9,<3.13
Classifier: License :: OSI Approved :: MIT License
Classifier: Programming Language :: Python :: 3
Classifier: Programming Language :: Python :: 3.9
Classifier: Programming Language :: Python :: 3.10
Classifier: Programming Language :: Python :: 3.11
Classifier: Programming Language :: Python :: 3.12
Requires-Dist: apischema (>=0.18.0,<0.19.0)
Requires-Dist: uai_openlabel (>=0.3.8,<0.4.0)
Project-URL: Repository, https://github.com/understand-ai/aveas_openlabel
